facecloak_suite/__init__.py
facecloak_suite-0.0.0a0.dist-info/METADATA
facecloak_suite-0.0.0a0.dist-info/WHEEL
facecloak_suite-0.0.0a0.dist-info/licenses/LICENSE
facecloak_suite-0.0.0a0.dist-info/RECORD
