Metadata-Version: 2.4
Name: facecloak-suite
Version: 0.0.0a0
Summary: Placeholder release — full code coming soon.
Author-email: Muntaser Syed <jemsbhai@gmail.com>
License: Apache-2.0
License-File: LICENSE
Classifier: Development Status :: 1 - Planning
Classifier: Intended Audience :: Developers
Classifier: License :: OSI Approved :: Apache Software License
Classifier: Programming Language :: Python :: 3
Requires-Python: >=3.9
